CHANGES.rst
LICENSE
MANIFEST.in
README.rst
setup.cfg
setup.py
tox.ini
docs/CHANGES.rst
docs/README.rst
docs/conf.py
docs/imports.rst
docs/index.rst
docs/install.rst
docs/userguide.rst
docs/_static/.keep
docs/_templates/.keep
examples/rmi.py
examples/jms/README.TXT
examples/jms/testJpypePublisher.py
examples/jms/testJpypeSubscriber.py
examples/linux/README.TXT
examples/linux/findjvm.py
examples/linux/jpype.sh
src/jt/__init__.py
src/jt/jpype/JClassUtil.py
src/jt/jpype/__about__.py
src/jt/jpype/__init__.py
src/jt/jpype/_classpath.py
src/jt/jpype/_config.py
src/jt/jpype/_cygwin.py
src/jt/jpype/_darwin.py
src/jt/jpype/_gui.py
src/jt/jpype/_jarray.py
src/jt/jpype/_jboxed.py
src/jt/jpype/_jclass.py
src/jt/jpype/_jexception.py
src/jt/jpype/_jpackage.py
src/jt/jpype/_jproxy.py
src/jt/jpype/_jvm.py
src/jt/jpype/_jvmfinder.py
src/jt/jpype/_jwrapper.py
src/jt/jpype/_linux.py
src/jt/jpype/_obsolete.py
src/jt/jpype/_windows.py
src/jt/jpype/imports.py
src/jt/jpype/nio.py
src/jt/jpype/reflect.py
src/jt/jpype/awt/__init__.py
src/jt/jpype/awt/event/__init__.py
src/jt/jpypex/__init__.py
src/jt/jpypex/swing/__init__.py
src/jt/jpypex/swing/pyutils.py
src/jtypes.jpype.egg-info/PKG-INFO
src/jtypes.jpype.egg-info/SOURCES.txt
src/jtypes.jpype.egg-info/dependency_links.txt
src/jtypes.jpype.egg-info/namespace_packages.txt
src/jtypes.jpype.egg-info/requires.txt
src/jtypes.jpype.egg-info/top_level.txt
src/jtypes.jpype.egg-info/zip-safe
tests/__init__.py
tests/__main__.py
tests/buf_leak_test.py
tests/buf_leak_test3.py
tests/convtest.py
tests/findjvm.py
tests/java_dom.py
tests/java_sax.py
tests/lists_and_maps.py
tests/python_dom.py
tests/run.py
tests/stub.py
tests/test_awt.py
tests/test_jarray_fixes.py
tests/testlucene.py
tests/testlucene_new.py
tests/testsuite.py
tests/classes/jpype/array/Test2.class
tests/classes/jpype/array/TestArray.class
tests/classes/jpype/attr/ClassWithBuffer.class
tests/classes/jpype/attr/Holder.class
tests/classes/jpype/attr/SubHolder.class
tests/classes/jpype/attr/SyntheticMethods$GenericImpl.class
tests/classes/jpype/attr/SyntheticMethods$GenericInterface.class
tests/classes/jpype/attr/SyntheticMethods.class
tests/classes/jpype/attr/Test1.class
tests/classes/jpype/attr/Test2.class
tests/classes/jpype/attr/TestOverloadA.class
